validator/__init__.py
validator/__main__.py
validator/cgit.py
validator/distgit.py
validator/exceptions.py
validator/format.py
validator/github.py
validator/global_session.py
validator/support.py
validator/schema/__init__.py
validator/schema/image_schema.py
validator/schema/modification_schema.py
validator/schema/releases_schema.py
validator/schema/rpm_schema.py
validator/schema/streams_schema.py
rh_ocp_build_data_validator-0.2.5.dist-info/LICENSE
rh_ocp_build_data_validator-0.2.5.dist-info/METADATA
rh_ocp_build_data_validator-0.2.5.dist-info/WHEEL
rh_ocp_build_data_validator-0.2.5.dist-info/entry_points.txt
rh_ocp_build_data_validator-0.2.5.dist-info/top_level.txt
rh_ocp_build_data_validator-0.2.5.dist-info/RECORD
