Metadata-Version: 2.1
Name: rh-ocp-build-data-validator
Version: 0.2.5
Summary: Validation of ocp-build-data Image & RPM declarations
Home-page: https://github.com/openshift/ocp-build-data-validator
Author: AOS ART Team
Author-email: aos-team-art@redhat.com
License: Apache License, Version 2.0
Platform: UNKNOWN
License-File: LICENSE
Requires-Dist: appdirs (==1.4.4)
Requires-Dist: bleach (==3.1.5)
Requires-Dist: certifi (==2020.4.5.1)
Requires-Dist: cffi (==1.14.0)
Requires-Dist: chardet (==3.0.4)
Requires-Dist: contextlib2 (==0.6.0.post1)
Requires-Dist: cryptography (==2.9.2)
Requires-Dist: distlib (==0.3.0)
Requires-Dist: docutils (==0.16)
Requires-Dist: filelock (==3.0.12)
Requires-Dist: future (==0.18.2)
Requires-Dist: idna (==2.9)
Requires-Dist: importlib-metadata (==1.6.1)
Requires-Dist: importlib-resources (==1.5.0)
Requires-Dist: jeepney (==0.4.3)
Requires-Dist: keyring (==21.2.1)
Requires-Dist: packaging (==20.4)
Requires-Dist: pkginfo (==1.5.0.1)
Requires-Dist: pluggy (==0.13.1)
Requires-Dist: py (==1.8.1)
Requires-Dist: pycparser (==2.20)
Requires-Dist: pygit2 (==1.6.*)
Requires-Dist: Pygments (==2.6.1)
Requires-Dist: pyparsing (==2.4.7)
Requires-Dist: PyYAML (==5.3.1)
Requires-Dist: readme-renderer (==26.0)
Requires-Dist: requests (==2.23.0)
Requires-Dist: requests-toolbelt (==0.9.1)
Requires-Dist: rpm (==0.0.2)
Requires-Dist: ruamel.yaml
Requires-Dist: schema (==0.7.2)
Requires-Dist: SecretStorage (==3.1.2)
Requires-Dist: six (==1.15.0)
Requires-Dist: toml (==0.10.1)
Requires-Dist: tqdm (==4.46.1)
Requires-Dist: twine (==3.1.1)
Requires-Dist: urllib3 (==1.25.9)
Requires-Dist: virtualenv (==20.0.21)
Requires-Dist: webencodings (==0.5.1)
Requires-Dist: zipp (==3.1.0)
